calmjs.types-1.0.0-py3.6-nspkg.pth
calmjs/types/__init__.py
calmjs/types/exceptions.py
calmjs/types/tests/__init__.py
calmjs/types/tests/test_exceptions.py
calmjs.types-1.0.0.dist-info/DESCRIPTION.rst
calmjs.types-1.0.0.dist-info/METADATA
calmjs.types-1.0.0.dist-info/RECORD
calmjs.types-1.0.0.dist-info/WHEEL
calmjs.types-1.0.0.dist-info/metadata.json
calmjs.types-1.0.0.dist-info/namespace_packages.txt
calmjs.types-1.0.0.dist-info/top_level.txt
