Metadata-Version: 2.0
Name: calmjs.types
Version: 1.0.0
Summary: Types for the calmjs framework.
Home-page: https://github.com/calmjs/calmjs.types
Author: Tommy Yu
Author-email: tommy.yu@auckland.ac.nz
License: mit
Platform: UNKNOWN
Classifier: Development Status :: 5 - Production/Stable
Classifier: Intended Audience :: Developers
Classifier: License :: OSI Approved :: MIT License
Classifier: Operating System :: OS Independent
Classifier: Programming Language :: Python :: 2.7
Classifier: Programming Language :: Python :: 3.3
Classifier: Programming Language :: Python :: 3.4
Classifier: Programming Language :: Python :: 3.5
Classifier: Programming Language :: Python :: 3.6
Requires-Dist: setuptools
